smartDocx/__init__.py
smartDocx/config.py
smartDocx/constants.py
smartDocx/report.py
smartDocx/utils.py
smartDocx/package/__init__.py
smartDocx/package/base.py
smartDocx/package/chart.py
smartDocx/package/content.py
smartDocx/package/paragraph.py
smartDocx/package/picture.py
smartDocx/package/table.py
smartDocx/package/title.py
smartDocx/templates/__init__.py
smartDocx/tmp/__init__.py
smartDocx-0.0.8.dist-info/LICENSE.txt
smartDocx-0.0.8.dist-info/METADATA
smartDocx-0.0.8.dist-info/WHEEL
smartDocx-0.0.8.dist-info/top_level.txt
smartDocx-0.0.8.dist-info/RECORD
