Metadata-Version: 2.1
Name: smartDocx
Version: 0.0.8
Summary: smart docx
Home-page: UNKNOWN
Author: sanbom
Author-email: sanbomsu1993@outlook.com
License: MIT
Platform: UNKNOWN
License-File: LICENSE.txt
Requires-Dist: xlrd (<2,>=1.2.0)
Requires-Dist: numpy (>=1.21.2)
Requires-Dist: openpyxl (>=3.0.9)
Requires-Dist: pandas (>=1.3.3)
Requires-Dist: pyecharts (>=1.9.0)
Requires-Dist: pyecharts-snapshot (>=0.2.0)
Requires-Dist: snapshot-phantomjs (>=0.0.3)
Requires-Dist: python-docx (>=0.8.11)
